Workbook

Sheet Ingresos por Unidad
B2: Ingresos por Unidad — Edificio Uruguay
B4: Unidad | C4: Ene | D4: Feb | E4: Mar | F4: Abr | G4: May | H4: Jun | I4: Jul | J4: Ago | K4: Sep | L4: Oct | M4: Nov | N4: Dic | O4: Total Anual
B5: Apto 1 | O5: =SUM(C5:N5)
B6: Apto 2 | O6: =SUM(C6:N6)
B7: Apto 3 | O7: =SUM(C7:N7)
B8: Apto 4 | O8: =SUM(C8:N8)
B9: Apto 5 | O9: =SUM(C9:N9)
B10: Apto 6 | O10: =SUM(C10:N10)
B11: Apto 7 | O11: =SUM(C11:N11)
B12: Apto 8 | O12: =SUM(C12:N12)
B13: Apto 9 | O13: =SUM(C13:N13)
B14: Apto 10 | O14: =SUM(C14:N14)
B15: Apto 11 | O15: =SUM(C15:N15)
B16: Apto 12 | O16: =SUM(C16:N16)
... B33: Local 2 | O33: =SUM(C33:N33)
B34: TOTAL INGRESOS | C34: =SUM(C5:C33) | D34: =SUM(D5:D33) | E34: =SUM(E5:E33) | F34: =SUM(F5:F33) | G34: =SUM(G5:G33) | H34: =SUM(H5:H33) | I34: =SUM(I5:I33) | J34: =SUM(J5:J33) | ... O34: =SUM(O5:O33)

Sheet Gastos del Edificio
B2: Gastos del Edificio — Edificio Uruguay
B4: Categoría | C4: Ene | D4: Feb | E4: Mar | F4: Abr | G4: May | H4: Jun | I4: Jul | J4: Ago | K4: Sep | L4: Oct | M4: Nov | N4: Dic | O4: Total Anual
B5: Expensas comunes | O5: =SUM(C5:N5)
B6: Impuesto Inmobiliario | O6: =SUM(C6:N6)
B7: Tributo DGI | O7: =SUM(C7:N7)
B8: Contribución Inmobiliaria | O8: =SUM(C8:N8)
B9: Agua (OSE) | O9: =SUM(C9:N9)
B10: Electricidad (UTE) - Areas comunes | O10: =SUM(C10:N10)
B11: Seguro del edificio | O11: =SUM(C11:N11)
B12: Mantenimiento ascensor | O12: =SUM(C12:N12)
B13: Limpieza | O13: =SUM(C13:N13)
B14: Seguridad / Vigilancia | O14: =SUM(C14:N14)
B15: Reparaciones | O15: =SUM(C15:N15)
B16: Mantenimiento general | O16: =SUM(C16:N16)
... B20: Otros | O20: =SUM(C20:N20)
B21: TOTAL GASTOS | C21: =SUM(C5:C20) | D21: =SUM(D5:D20) | E21: =SUM(E5:E20) | F21: =SUM(F5:F20) | G21: =SUM(G5:G20) | H21: =SUM(H5:H20) | I21: =SUM(I5:I20) | J21: =SUM(J5:J20) | ... O21: =SUM(O5:O20)

Sheet Resumen Balance
B2: Resumen Balance Anual — Edificio Uruguay
B4: Concepto | C4: Ene | D4: Feb | E4: Mar | F4: Abr | G4: May | H4: Jun | I4: Jul | J4: Ago | K4: Sep | L4: Oct | M4: Nov | N4: Dic | O4: Total Anual
B5: Total Ingresos | C5: ='Ingresos por Unidad'!C34 | D5: ='Ingresos por Unidad'!D34 | E5: ='Ingresos por Unidad'!E34 | F5: ='Ingresos por Unidad'!F34 | G5: ='Ingresos por Unidad'!G34 | H5: ='Ingresos por Unidad'!H34 | I5: ='Ingresos por Unidad'!I34 | J5: ='Ingresos por Unidad'!J34 | ... N5: ='Ingresos por Unidad'!N34 | O5: =SUM(C5:N5)
B6: Total Gastos | C6: ='Gastos del Edificio'!C21 | D6: ='Gastos del Edificio'!D21 | E6: ='Gastos del Edificio'!E21 | F6: ='Gastos del Edificio'!F21 | G6: ='Gastos del Edificio'!G21 | H6: ='Gastos del Edificio'!H21 | I6: ='Gastos del Edificio'!I21 | J6: ='Gastos del Edificio'!J21 | ... N6: ='Gastos del Edificio'!N21 | O6: =SUM(C6:N6)
B7: BALANCE | C7: =C5-C6 | D7: =D5-D6 | E7: =E5-E6 | F7: =F5-F6 | G7: =G5-G6 | H7: =H5-H6 | I7: =I5-I6 | J7: =J5-J6 | ... O7: =O5-O6
B9: Desglose proporcional por unidad
B10: Unidad | C10: Ene | D10: Feb | E10: Mar | F10: Abr | G10: May | H10: Jun | I10: Jul | J10: Ago | K10: Sep | L10: Oct | M10: Nov | N10: Dic | O10: Total Anual
B11: Apto 1 | C11: =IFERROR(C6/29,0) | D11: =IFERROR(D6/29,0) | E11: =IFERROR(E6/29,0) | F11: =IFERROR(F6/29,0) | G11: =IFERROR(G6/29,0) | H11: =IFERROR(H6/29,0) | I11: =IFERROR(I6/29,0) | J11: =IFERROR(J6/29,0) | ... N11: =IFERROR(N6/29,0) | O11: =SUM(C11:N11)
B12: Apto 2 | C12: =IFERROR(C6/29,0) | D12: =IFERROR(D6/29,0) | E12: =IFERROR(E6/29,0) | F12: =IFERROR(F6/29,0) | G12: =IFERROR(G6/29,0) | H12: =IFERROR(H6/29,0) | I12: =IFERROR(I6/29,0) | J12: =IFERROR(J6/29,0) | ... N12: =IFERROR(N6/29,0) | O12: =SUM(C12:N12)
B13: Apto 3 | C13: =IFERROR(C6/29,0) | D13: =IFERROR(D6/29,0) | E13: =IFERROR(E6/29,0) | F13: =IFERROR(F6/29,0) | G13: =IFERROR(G6/29,0) | H13: =IFERROR(H6/29,0) | I13: =IFERROR(I6/29,0) | J13: =IFERROR(J6/29,0) | ... N13: =IFERROR(N6/29,0) | O13: =SUM(C13:N13)
B14: Apto 4 | C14: =IFERROR(C6/29,0) | D14: =IFERROR(D6/29,0) | E14: =IFERROR(E6/29,0) | F14: =IFERROR(F6/29,0) | G14: =IFERROR(G6/29,0) | H14: =IFERROR(H6/29,0) | I14: =IFERROR(I6/29,0) | J14: =IFERROR(J6/29,0) | ... N14: =IFERROR(N6/29,0) | O14: =SUM(C14:N14)
B15: Apto 5 | C15: =IFERROR(C6/29,0) | D15: =IFERROR(D6/29,0) | E15: =IFERROR(E6/29,0) | F15: =IFERROR(F6/29,0) | G15: =IFERROR(G6/29,0) | H15: =IFERROR(H6/29,0) | I15: =IFERROR(I6/29,0) | J15: =IFERROR(J6/29,0) | ... N15: =IFERROR(N6/29,0) | O15: =SUM(C15:N15)
B16: Apto 6 | C16: =IFERROR(C6/29,0) | D16: =IFERROR(D6/29,0) | E16: =IFERROR(E6/29,0) | F16: =IFERROR(F6/29,0) | G16: =IFERROR(G6/29,0) | H16: =IFERROR(H6/29,0) | I16: =IFERROR(I6/29,0) | J16: =IFERROR(J6/29,0) | ... N16: =IFERROR(N6/29,0) | O16: =SUM(C16:N16)
B17: Apto 7 | C17: =IFERROR(C6/29,0) | D17: =IFERROR(D6/29,0) | E17: =IFERROR(E6/29,0) | F17: =IFERROR(F6/29,0) | G17: =IFERROR(G6/29,0) | H17: =IFERROR(H6/29,0) | I17: =IFERROR(I6/29,0) | J17: =IFERROR(J6/29,0) | ... N17: =IFERROR(N6/29,0) | O17: =SUM(C17:N17)
B18: Apto 8 | C18: =IFERROR(C6/29,0) | D18: =IFERROR(D6/29,0) | E18: =IFERROR(E6/29,0) | F18: =IFERROR(F6/29,0) | G18: =IFERROR(G6/29,0) | H18: =IFERROR(H6/29,0) | I18: =IFERROR(I6/29,0) | J18: =IFERROR(J6/29,0) | ... N18: =IFERROR(N6/29,0) | O18: =SUM(C18:N18)
B19: Apto 9 | C19: =IFERROR(C6/29,0) | D19: =IFERROR(D6/29,0) | E19: =IFERROR(E6/29,0) | F19: =IFERROR(F6/29,0) | G19: =IFERROR(G6/29,0) | H19: =IFERROR(H6/29,0) | I19: =IFERROR(I6/29,0) | J19: =IFERROR(J6/29,0) | ... N19: =IFERROR(N6/29,0) | O19: =SUM(C19:N19)
B20: Apto 10 | C20: =IFERROR(C6/29,0) | D20: =IFERROR(D6/29,0) | E20: =IFERROR(E6/29,0) | F20: =IFERROR(F6/29,0) | G20: =IFERROR(G6/29,0) | H20: =IFERROR(H6/29,0) | I20: =IFERROR(I6/29,0) | J20: =IFERROR(J6/29,0) | ... N20: =IFERROR(N6/29,0) | O20: =SUM(C20:N20)
B21: Apto 11 | C21: =IFERROR(C6/29,0) | D21: =IFERROR(D6/29,0) | E21: =IFERROR(E6/29,0) | F21: =IFERROR(F6/29,0) | G21: =IFERROR(G6/29,0) | H21: =IFERROR(H6/29,0) | I21: =IFERROR(I6/29,0) | J21: =IFERROR(J6/29,0) | ... N21: =IFERROR(N6/29,0) | O21: =SUM(C21:N21)
B22: Apto 12 | C22: =IFERROR(C6/29,0) | D22: =IFERROR(D6/29,0) | E22: =IFERROR(E6/29,0) | F22: =IFERROR(F6/29,0) | G22: =IFERROR(G6/29,0) | H22: =IFERROR(H6/29,0) | I22: =IFERROR(I6/29,0) | J22: =IFERROR(J6/29,0) | ... N22: =IFERROR(N6/29,0) | O22: =SUM(C22:N22)
B23: Apto 13 | C23: =IFERROR(C6/29,0) | D23: =IFERROR(D6/29,0) | E23: =IFERROR(E6/29,0) | F23: =IFERROR(F6/29,0) | G23: =IFERROR(G6/29,0) | H23: =IFERROR(H6/29,0) | I23: =IFERROR(I6/29,0) | J23: =IFERROR(J6/29,0) | ... N23: =IFERROR(N6/29,0) | O23: =SUM(C23:N23)
B24: Apto 14 | C24: =IFERROR(C6/29,0) | D24: =IFERROR(D6/29,0) | E24: =IFERROR(E6/29,0) | F24: =IFERROR(F6/29,0) | G24: =IFERROR(G6/29,0) | H24: =IFERROR(H6/29,0) | I24: =IFERROR(I6/29,0) | J24: =IFERROR(J6/29,0) | ... N24: =IFERROR(N6/29,0) | O24: =SUM(C24:N24)
B25: Apto 15 | C25: =IFERROR(C6/29,0) | D25: =IFERROR(D6/29,0) | E25: =IFERROR(E6/29,0) | F25: =IFERROR(F6/29,0) | G25: =IFERROR(G6/29,0) | H25: =IFERROR(H6/29,0) | I25: =IFERROR(I6/29,0) | J25: =IFERROR(J6/29,0) | ... N25: =IFERROR(N6/29,0) | O25: =SUM(C25:N25)
B26: Apto 16 | C26: =IFERROR(C6/29,0) | D26: =IFERROR(D6/29,0) | E26: =IFERROR(E6/29,0) | F26: =IFERROR(F6/29,0) | G26: =IFERROR(G6/29,0) | H26: =IFERROR(H6/29,0) | I26: =IFERROR(I6/29,0) | J26: =IFERROR(J6/29,0) | ... N26: =IFERROR(N6/29,0) | O26: =SUM(C26:N26)
B27: Apto 17 | C27: =IFERROR(C6/29,0) | D27: =IFERROR(D6/29,0) | E27: =IFERROR(E6/29,0) | F27: =IFERROR(F6/29,0) | G27: =IFERROR(G6/29,0) | H27: =IFERROR(H6/29,0) | I27: =IFERROR(I6/29,0) | J27: =IFERROR(J6/29,0) | ... N27: =IFERROR(N6/29,0) | O27: =SUM(C27:N27)
B28: Apto 18 | C28: =IFERROR(C6/29,0) | D28: =IFERROR(D6/29,0) | E28: =IFERROR(E6/29,0) | F28: =IFERROR(F6/29,0) | G28: =IFERROR(G6/29,0) | H28: =IFERROR(H6/29,0) | I28: =IFERROR(I6/29,0) | J28: =IFERROR(J6/29,0) | ... N28: =IFERROR(N6/29,0) | O28: =SUM(C28:N28)
B29: Apto 19 | C29: =IFERROR(C6/29,0) | D29: =IFERROR(D6/29,0) | E29: =IFERROR(E6/29,0) | F29: =IFERROR(F6/29,0) | G29: =IFERROR(G6/29,0) | H29: =IFERROR(H6/29,0) | I29: =IFERROR(I6/29,0) | J29: =IFERROR(J6/29,0) | ... N29: =IFERROR(N6/29,0) | O29: =SUM(C29:N29)
B30: Apto 20 | C30: =IFERROR(C6/29,0) | D30: =IFERROR(D6/29,0) | E30: =IFERROR(E6/29,0) | F30: =IFERROR(F6/29,0) | G30: =IFERROR(G6/29,0) | H30: =IFERROR(H6/29,0) | I30: =IFERROR(I6/29,0) | J30: =IFERROR(J6/29,0) | ... N30: =IFERROR(N6/29,0) | O30: =SUM(C30:N30)
B31: Apto 21 | C31: =IFERROR(C6/29,0) | D31: =IFERROR(D6/29,0) | E31: =IFERROR(E6/29,0) | F31: =IFERROR(F6/29,0) | G31: =IFERROR(G6/29,0) | H31: =IFERROR(H6/29,0) | I31: =IFERROR(I6/29,0) | J31: =IFERROR(J6/29,0) | ... N31: =IFERROR(N6/29,0) | O31: =SUM(C31:N31)
B32: Apto 22 | C32: =IFERROR(C6/29,0) | D32: =IFERROR(D6/29,0) | E32: =IFERROR(E6/29,0) | F32: =IFERROR(F6/29,0) | G32: =IFERROR(G6/29,0) | H32: =IFERROR(H6/29,0) | I32: =IFERROR(I6/29,0) | J32: =IFERROR(J6/29,0) | ... N32: =IFERROR(N6/29,0) | O32: =SUM(C32:N32)
B33: Apto 23 | C33: =IFERROR(C6/29,0) | D33: =IFERROR(D6/29,0) | E33: =IFERROR(E6/29,0) | F33: =IFERROR(F6/29,0) | G33: =IFERROR(G6/29,0) | H33: =IFERROR(H6/29,0) | I33: =IFERROR(I6/29,0) | J33: =IFERROR(J6/29,0) | ... N33: =IFERROR(N6/29,0) | O33: =SUM(C33:N33)
B34: Apto 24 | C34: =IFERROR(C6/29,0) | D34: =IFERROR(D6/29,0) | E34: =IFERROR(E6/29,0) | F34: =IFERROR(F6/29,0) | G34: =IFERROR(G6/29,0) | H34: =IFERROR(H6/29,0) | I34: =IFERROR(I6/29,0) | J34: =IFERROR(J6/29,0) | ... N34: =IFERROR(N6/29,0) | O34: =SUM(C34:N34)
B35: Apto 25 | C35: =IFERROR(C6/29,0) | D35: =IFERROR(D6/29,0) | E35: =IFERROR(E6/29,0) | F35: =IFERROR(F6/29,0) | G35: =IFERROR(G6/29,0) | H35: =IFERROR(H6/29,0) | I35: =IFERROR(I6/29,0) | J35: =IFERROR(J6/29,0) | ... N35: =IFERROR(N6/29,0) | O35: =SUM(C35:N35)
B36: Apto 26 | C36: =IFERROR(C6/29,0) | D36: =IFERROR(D6/29,0) | E36: =IFERROR(E6/29,0) | F36: =IFERROR(F6/29,0) | G36: =IFERROR(G6/29,0) | H36: =IFERROR(H6/29,0) | I36: =IFERROR(I6/29,0) | J36: =IFERROR(J6/29,0) | ... N36: =IFERROR(N6/29,0) | O36: =SUM(C36:N36)
B37: Apto 27 | C37: =IFERROR(C6/29,0) | D37: =IFERROR(D6/29,0) | E37: =IFERROR(E6/29,0) | F37: =IFERROR(F6/29,0) | G37: =IFERROR(G6/29,0) | H37: =IFERROR(H6/29,0) | I37: =IFERROR(I6/29,0) | J37: =IFERROR(J6/29,0) | ... N37: =IFERROR(N6/29,0) | O37: =SUM(C37:N37)
B38: Local 1 | C38: =IFERROR(C6/29,0) | D38: =IFERROR(D6/29,0) | E38: =IFERROR(E6/29,0) | F38: =IFERROR(F6/29,0) | G38: =IFERROR(G6/29,0) | H38: =IFERROR(H6/29,0) | I38: =IFERROR(I6/29,0) | J38: =IFERROR(J6/29,0) | ... N38: =IFERROR(N6/29,0) | O38: =SUM(C38:N38)
B39: Local 2 | C39: =IFERROR(C6/29,0) | D39: =IFERROR(D6/29,0) | E39: =IFERROR(E6/29,0) | F39: =IFERROR(F6/29,0) | G39: =IFERROR(G6/29,0) | H39: =IFERROR(H6/29,0) | I39: =IFERROR(I6/29,0) | J39: =IFERROR(J6/29,0) | ... N39: =IFERROR(N6/29,0) | O39: =SUM(C39:N39)
B40: Verificación (suma) | C40: =SUM(C11:C39) | D40: =SUM(D11:D39) | E40: =SUM(E11:E39) | F40: =SUM(F11:F39) | G40: =SUM(G11:G39) | H40: =SUM(H11:H39) | I40: =SUM(I11:I39) | J40: =SUM(J11:J39) | ... O40: =SUM(O11:O39)
